riverlakenetwork/__init__.py
riverlakenetwork/burn_lakes.py
riverlakenetwork/input_checker.py
riverlakenetwork/input_loader.py
riverlakenetwork/network_checker.py
riverlakenetwork/network_correction.py
riverlakenetwork/output_checker.py
riverlakenetwork/resolvable_lake_identifier.py
riverlakenetwork/utility.py
riverlakenetwork-0.0.0.dist-info/licenses/LICENSE
riverlakenetwork-0.0.0.dist-info/METADATA
riverlakenetwork-0.0.0.dist-info/WHEEL
riverlakenetwork-0.0.0.dist-info/top_level.txt
riverlakenetwork-0.0.0.dist-info/RECORD
