Metadata-Version: 2.4
Name: riverlakenetwork
Version: 0.0.0
Summary: Tools for river–lake network topology construction and validation
Author-email: Shervan Gharari <sh.gharari@gmail.com>
License: GPL-3.0-only
Project-URL: Homepage, https://github.com/ShervanGharari/RiverLakeNetwork
Project-URL: Repository, https://github.com/ShervanGharari/RiverLakeNetwork
Project-URL: Issues, https://github.com/ShervanGharari/RiverLakeNetwork/issues
Keywords: hydrology,river network,lake network,topology,geospatial
Classifier: License :: OSI Approved :: GNU General Public License v3 (GPLv3)
Classifier: Programming Language :: Python :: 3
Classifier: Programming Language :: Python :: 3 :: Only
Classifier: Programming Language :: Python :: 3.9
Classifier: Programming Language :: Python :: 3.10
Classifier: Programming Language :: Python :: 3.11
Classifier: Intended Audience :: Science/Research
Classifier: Topic :: Scientific/Engineering :: Hydrology
Requires-Python: >=3.8
License-File: LICENSE
Requires-Dist: numpy
Requires-Dist: pandas
Requires-Dist: geopandas
Requires-Dist: shapely
Requires-Dist: networkx
Requires-Dist: pyyaml
Provides-Extra: plot
Requires-Dist: matplotlib; extra == "plot"
Provides-Extra: dev
Requires-Dist: pytest; extra == "dev"
Requires-Dist: black; extra == "dev"
Requires-Dist: isort; extra == "dev"
Requires-Dist: flake8; extra == "dev"
Requires-Dist: build; extra == "dev"
Requires-Dist: twine; extra == "dev"
Dynamic: license-file
